docapi/__init__.py
docapi/docapi.py
docapi/llm/__init__.py
docapi/llm/azure_openai_llm.py
docapi/llm/baidu_llm.py
docapi/llm/base_llm.py
docapi/llm/llm_builder.py
docapi/llm/openai_llm.py
docapi/llm/zhipu_llm.py
docapi/main.py
docapi/prompt/__init__.py
docapi/prompt/doc_en.py
docapi/prompt/doc_zh.py
docapi/prompt/prompt_builder.py
docapi/scanner/__init__.py
docapi/scanner/base_scanner.py
docapi/scanner/django_scanner.py
docapi/scanner/flask_scanner.py
docapi/scanner/flask_static_scanner.py
docapi/scanner/scanner_builder.py
docapi/template/__init__.py
docapi/template/flask_en.md
docapi/template/flask_zh.md
docapi/template/template_builder.py
docapi/web/__init__.py
docapi/web/web_builder.py
docapi-1.1.14.dist-info/LICENSE
docapi-1.1.14.dist-info/METADATA
docapi-1.1.14.dist-info/WHEEL
docapi-1.1.14.dist-info/entry_points.txt
docapi-1.1.14.dist-info/RECORD
