Metadata-Version: 2.3
Name: docapi
Version: 1.1.14
Summary: DocAPI is a Python package that automatically generates API documentation using LLMs. It currently supports Flask and Django frameworks.
License: Apache-2.0
Author: zhangshulin
Author-email: zhangslwork@yeah.net
Requires-Python: >=3.8,<4
Classifier: License :: OSI Approved :: Apache Software License
Classifier: Programming Language :: Python :: 3
Classifier: Programming Language :: Python :: 3.8
Classifier: Programming Language :: Python :: 3.9
Classifier: Programming Language :: Python :: 3.10
Classifier: Programming Language :: Python :: 3.11
Classifier: Programming Language :: Python :: 3.12
Classifier: Programming Language :: Python :: 3.13
Provides-Extra: all
Provides-Extra: django
Provides-Extra: flask
Requires-Dist: django (>=3.0.0) ; extra == "django" or extra == "all"
Requires-Dist: fire (>=0.7.0,<0.8.0)
Requires-Dist: flask (>=3.0.0,<4.0.0) ; extra == "flask" or extra == "all"
Requires-Dist: ipython (>=8.0.0,<9.0.0)
Requires-Dist: mkdocs (>=1.6.1,<2.0.0)
Requires-Dist: openai (>=1.35.8,<2.0.0)
Requires-Dist: python-dotenv (>=1.0.1,<2.0.0)
Requires-Dist: pyyaml (>=6.0.2,<7.0.0)
Requires-Dist: qianfan (>=0.4.12.1,<0.5.0.0)
Requires-Dist: tqdm (>=4.67.1,<5.0.0)
Requires-Dist: zhipuai (>=2.1.5.20230904,<3.0.0.0)
Project-URL: Repository, https://github.com/NewToolAI/docapi
